withoutbg/__init__.py
withoutbg/__version__.py
withoutbg/api.py
withoutbg/cli.py
withoutbg/core.py
withoutbg/exceptions.py
withoutbg/models.py
withoutbg/py.typed
withoutbg-1.0.0.dist-info/METADATA
withoutbg-1.0.0.dist-info/WHEEL
withoutbg-1.0.0.dist-info/entry_points.txt
withoutbg-1.0.0.dist-info/RECORD
