Metadata-Version: 2.4
Name: withoutbg
Version: 1.0.0
Summary: AI-powered background removal with local and cloud options
Project-URL: Homepage, https://withoutbg.com
Project-URL: Repository, https://github.com/withoutbg/withoutbg
Project-URL: Documentation, https://withoutbg.com/documentation
Project-URL: Bug Reports, https://github.com/withoutbg/withoutbg/issues
Author-email: withoutbg <contact@withoutbg.com>
License: Apache-2.0
Keywords: ai,background-removal,computer-vision,image-processing,onnx
Classifier: Development Status :: 4 - Beta
Classifier: Intended Audience :: Developers
Classifier: License :: OSI Approved :: Apache Software License
Classifier: Programming Language :: Python :: 3
Classifier: Programming Language :: Python :: 3.9
Classifier: Programming Language :: Python :: 3.10
Classifier: Programming Language :: Python :: 3.11
Classifier: Programming Language :: Python :: 3.12
Classifier: Topic :: Multimedia :: Graphics :: Graphics Conversion
Classifier: Topic :: Scientific/Engineering :: Artificial Intelligence
Requires-Python: >=3.9
Requires-Dist: click>=8.0.0
Requires-Dist: huggingface-hub>=0.33.5
Requires-Dist: numpy>=1.21.0
Requires-Dist: onnxruntime<1.20.0,>=1.12.0
Requires-Dist: pillow>=8.0.0
Requires-Dist: requests>=2.25.0
Requires-Dist: tqdm>=4.60.0
Provides-Extra: dev
Requires-Dist: black>=22.0.0; extra == 'dev'
Requires-Dist: mypy>=1.0.0; extra == 'dev'
Requires-Dist: pre-commit>=2.20.0; extra == 'dev'
Requires-Dist: pytest-cov>=4.0.0; extra == 'dev'
Requires-Dist: pytest>=7.0.0; extra == 'dev'
Requires-Dist: ruff>=0.1.0; extra == 'dev'
Requires-Dist: types-pillow>=10.2.0; extra == 'dev'
Requires-Dist: types-requests>=2.32.0; extra == 'dev'
